{
    "docs": [
        {
            "id": "5eb87cd9ffd86e000604b32a",
            "name": "Falcon 1",
            "date_utc": "2006-03-24T22:30:00.000Z",
            "success": true,
            "rocket": {
                "name": "Falcon",
                "type": "v1.0",
                "id": "falcon1"
            },
            "links": {
                "patch": {
                    "small": "https://example.com/small_patch.png",
                    "large": "https://example.com/large_patch.png"
                },
                "youtube_id": "abcd1234",
                "article": "https://example.com/article",
                "wikipedia": "https://example.com/wikipedia"
            }
        }
    ]
}

